.coveragerc
.dockerignore
.gitattributes
.pre-commit-config.yaml
ChangeLog
LICENSE
README.md
logo.jpg
requirements.sh
requirements.txt
setup.cfg
setup.py
strategy.ini
.github/workflows/publish-pypi.yml
.github/workflows/unit-tests.yml
academic_observatory_workflows/__init__.py
academic_observatory_workflows/clearbit.py
academic_observatory_workflows/config.py
academic_observatory_workflows/model.py
academic_observatory_workflows.egg-info/PKG-INFO
academic_observatory_workflows.egg-info/SOURCES.txt
academic_observatory_workflows.egg-info/dependency_links.txt
academic_observatory_workflows.egg-info/not-zip-safe
academic_observatory_workflows.egg-info/pbr.json
academic_observatory_workflows.egg-info/requires.txt
academic_observatory_workflows.egg-info/top_level.txt
academic_observatory_workflows/dags/__init__.py
academic_observatory_workflows/dags/crossref_events_telescope.py
academic_observatory_workflows/dags/crossref_fundref_telescope.py
academic_observatory_workflows/dags/crossref_metadata_telescope.py
academic_observatory_workflows/dags/doi_workflow.py
academic_observatory_workflows/dags/elastic_import_workflow.py
academic_observatory_workflows/dags/geonames_telescope.py
academic_observatory_workflows/dags/grid_telescope.py
academic_observatory_workflows/dags/mag_telescope.py
academic_observatory_workflows/dags/oa_web_workflow.py
academic_observatory_workflows/dags/open_citations_telescope.py
academic_observatory_workflows/dags/openalex_telescope.py
academic_observatory_workflows/dags/orcid_telescope.py
academic_observatory_workflows/dags/ror_telescope.py
academic_observatory_workflows/dags/scopus_telescope.py
academic_observatory_workflows/dags/unpaywall_snapshot_telescope.py
academic_observatory_workflows/dags/unpaywall_telescope.py
academic_observatory_workflows/dags/web_of_science_telescope.py
academic_observatory_workflows/database/__init__.py
academic_observatory_workflows/database/mappings/__init__.py
academic_observatory_workflows/database/mappings/ao-access-types-mappings.json.jinja2
academic_observatory_workflows/database/mappings/ao-disciplines-mappings.json.jinja2
academic_observatory_workflows/database/mappings/ao-dois-mappings.json
academic_observatory_workflows/database/mappings/ao-events-mappings.json.jinja2
academic_observatory_workflows/database/mappings/ao-metrics-mappings.json.jinja2
