Metadata-Version: 2.1
Name: academic-observatory-workflows
Version: 2022.3.0
Summary: Academic Observatory Workflows provides Apache Airflow Workflows for fetching, processing and analysing data about academic institutions.
Home-page: https://github.com/The-Academic-Observatory/academic-observatory-workflows
Author: Curtin University
Author-email: agent@observatory.academy
License: Apache License Version 2.0
Project-URL: Bug Tracker, https://github.com/The-Academic-Observatory/academic-observatory-workflows/issues
Project-URL: Documentation, https://academic-observatory-workflows.readthedocs.io/en/latest/
Project-URL: Source Code, https://github.com/The-Academic-Observatory/academic-observatory-workflows
Keywords: science,data,workflows,academic institutes,academic-observatory-workflows
Platform: UNKNOWN
Classifier: Development Status :: 2 - Pre-Alpha
Classifier: Environment :: Console
Classifier: Environment :: Web Environment
Classifier: Intended Audience :: Developers
Classifier: Intended Audience :: Science/Research
Classifier: License :: OSI Approved :: Apache Software License
Classifier: Operating System :: OS Independent
Classifier: Programming Language :: Python :: 3 :: Only
Classifier: Programming Language :: Python :: 3
Classifier: Programming Language :: Python :: 3.7
Classifier: Topic :: Scientific/Engineering
Classifier: Topic :: Software Development :: Libraries
Classifier: Topic :: Software Development :: Libraries :: Python Modules
Classifier: Topic :: Utilities
Requires-Python: >=3.7
Provides-Extra: tests
